contained.py
contained-0.0.2.dist-info/LICENSE
contained-0.0.2.dist-info/WHEEL
contained-0.0.2.dist-info/METADATA
contained-0.0.2.dist-info/RECORD
