Metadata-Version: 2.1
Name: contained
Version: 0.0.2
Summary: Enable function chaining for any object
Keywords: functional,composition,pipline,chaining
Author-email: Jeremiah Paige <ucodery@gmail.com>
Requires-Python: >=3.8
Classifier: License :: OSI Approved :: MIT License
Requires-Dist: flit ; extra == "dev"
Requires-Dist: nox ; extra == "dev"
Requires-Dist: pytest >= 2.7.3 ; extra == "test"
Requires-Dist: mktestdocs >= 0.2.0 ; extra == "test"
Project-URL: Home, https://github.com/ucodery/contained
Provides-Extra: dev
Provides-Extra: test
